nnie/__init__.py
nnie/blob.py
nnie/nnie.py
nnie-0.1.dist-info/LICENSE
nnie-0.1.dist-info/METADATA
nnie-0.1.dist-info/WHEEL
nnie-0.1.dist-info/top_level.txt
nnie-0.1.dist-info/RECORD
