Metadata-Version: 2.1
Name: nnie
Version: 0.1
Summary: NNIE Python Interface
Home-page: https://github.com/sunnyden/nnie_python_remote_interface
Author: Haoqing Deng
Author-email: dhq.sunny@gmail.com
License: MIT
Platform: UNKNOWN
Classifier: Programming Language :: Python :: 3
Classifier: License :: OSI Approved :: MIT License
Classifier: Operating System :: OS Independent
Requires-Dist: opencv-python
Requires-Dist: numpy
